numerai_reports/__init__.py
numerai_reports/data.py
numerai_reports/flow.py
numerai_reports/leaderboard.py
numerai_reports/mytest_uuazed3.py
numerai_reports/reports.py
numerai_reports/settings.py
numerai_reports/test.py
numerai_reports/test_uuazed3.py
numerai_reports/utils.py
numerai_reports-0.5.5.dist-info/METADATA
numerai_reports-0.5.5.dist-info/WHEEL
numerai_reports-0.5.5.dist-info/top_level.txt
numerai_reports-0.5.5.dist-info/RECORD
