Metadata-Version: 2.1
Name: numerai-reports
Version: 0.5.5
Summary: Reports for the Numerai machine learning competition
Home-page: https://github.com/uuazed/numerai_reports
Maintainer: uuazed
Maintainer-email: uuazed@gmail.com
License: MIT License
Platform: OS Independent
Classifier: Development Status :: 3 - Alpha
Classifier: Environment :: Console
Classifier: Intended Audience :: Science/Research
Classifier: License :: OSI Approved :: MIT License
Classifier: Operating System :: OS Independent
Classifier: Programming Language :: Python
Classifier: Programming Language :: Python :: 3
Classifier: Topic :: Scientific/Engineering
Requires-Dist: pandas
Requires-Dist: numerapi
Requires-Dist: pyarrow
Requires-Dist: fsspec
Requires-Dist: gcsfs
